Metadata-Version: 2.1
Name: terminaal
Version: 0.1
Summary: Address Book Assistant Bot
Home-page: https://github.com/alexvekh/project-team-8-Personal-assistant
Author: Vladyslav Babenko, Oleksy Verkhulevskyy, Aliesia Soloviova, Daniel Prokopenko, Marichka Matviiuk, Maks Pryima
Author-email: vlad_bb@icloud.com, alexvekh@yahoo.com, aliesia.soloviova@gmail.com, megaprokop3578@gmail.com, m.v.matviiuk@gmail.com, makspryima@gmail.com
License: MIT
